systemdumpy/__about__.py
systemdumpy/__main__.py
systemdumpy/modules/BrDataObjectFile.py
systemdumpy/modules/BrFile.py
systemdumpy/modules/BrLoggerFile.py
systemdumpy/modules/__init__.py
systemdumpy/modules/datafiles.py
systemdumpy/modules/report.py
systemdumpy/modules/web.py
systemdumpy-1.0.3.dist-info/METADATA
systemdumpy-1.0.3.dist-info/WHEEL
systemdumpy-1.0.3.dist-info/licenses/LICENSE
systemdumpy-1.0.3.dist-info/RECORD
