Metadata-Version: 2.1
Name: systemdumpy
Version: 1.0.3
Summary: create and load a system dump for B&R PLC from the command line
Project-URL: Homepage, https://github.com/hilch/systemdump.py
Project-URL: Bug Tracker, https://github.com/hilch/systemdump.py/issues
Author: Christoph Hilchenbach
License-File: LICENSE
Classifier: License :: OSI Approved :: MIT License
Classifier: Operating System :: OS Independent
Classifier: Programming Language :: Python :: 3
Requires-Python: >=3.8
Requires-Dist: openpyxl>=3.1.2
Requires-Dist: requests>=2.31.0
